[
  {
    "id": "1",
    "country": "USA",
    "image": "https://example.com/usa.jpg",
    "visa_type": "Tourist Visa",
    "processing_time": 10,
    "fee": 160,
    "validity": 6,
    "application_method": "Online"
  },
  {
    "id": "2",
    "country": "Canada",
    "image": "https://example.com/canada.jpg",
    "visa_type": "Student Visa",
    "processing_time": 15,
    "fee": 150,
    "validity": 12,
    "application_method": "Online"
  },
  {
    "id": "3",
    "country": "Australia",
    "image": "https://example.com/australia.jpg",
    "visa_type": "Work Visa",
    "processing_time": 20,
    "fee": 200,
    "validity": 24,
    "application_method": "Online"
  },
  {
    "id": "4",
    "country": "UK",
    "image": "https://example.com/uk.jpg",
    "visa_type": "Business Visa",
    "processing_time": 7,
    "fee": 180,
    "validity": 12,
    "application_method": "Online"
  },
  {
    "id": "5",
    "country": "Japan",
    "image": "https://example.com/japan.jpg",
    "visa_type": "Tourist Visa",
    "processing_time": 5,
    "fee": 120,
    "validity": 3,
    "application_method": "Online"
  },
  {
    "id": "6",
    "country": "Germany",
    "image": "https://example.com/germany.jpg",
    "visa_type": "Work Visa",
    "processing_time": 12,
    "fee": 190,
    "validity": 12,
    "application_method": "Online"
  }
]
